vrz/cli.py
vrz/core.py
vrz/git_utils.py
vrz/poetry_utils.py
vrz-0.31.0.dist-info/LICENSE
vrz-0.31.0.dist-info/METADATA
vrz-0.31.0.dist-info/WHEEL
vrz-0.31.0.dist-info/entry_points.txt
vrz-0.31.0.dist-info/RECORD
