Metadata-Version: 2.3
Name: vrz
Version: 0.31.0
Summary: 
Author: Henryk Konsek
Author-email: hekonsek@gmail.com
Requires-Python: >=3.12
Classifier: Programming Language :: Python :: 3
Classifier: Programming Language :: Python :: 3.12
Classifier: Programming Language :: Python :: 3.13
Requires-Dist: requests (>=2.32.3,<3.0.0)
Requires-Dist: semver (>=3,<4)
Requires-Dist: typer (>=0.16.1)
